{
    "common": {
        "loading": "Indlæser...",
        "error": "Noget gik galt",
        "unexpectedError": "Der opstod en uventet fejl",
        "save": "Gem",
        "cancel": "Annuller",
        "delete": "Slet"
    },
    "auth": {
        "signIn": "Log ind",
        "signUp": "Start gratis",
        "email": "E-mailadresse",
        "password": "Adgangskode",
        "passwordHint": "Adgangskode (min. 6 tegn)",
        "forgotPassword": "Glemt adgangskode?",
        "forgotPasswordSubtitle": "Indtast din e-mail for at modtage et nulstillingslink.",
        "resetPassword": "Nulstil adgangskode",
        "sendResetLink": "Send nulstillingslink",
        "loadingSendReset": "Sender link...",
        "backToLogin": "Tilbage til login",
        "noAccount": "Har du ikke en konto?",
        "createAccount": "Opret konto",
        "alreadyHaveAccount": "Har du allerede en konto?",
        "signInTitle": "Log ind på Paktio",
        "signInSubtitle": "Skandinavisk minimalistisk præcision for dine aftaler.",
        "signUpTitle": "Opret din konto",
        "signUpSubtitle": "Bliv en del af fremtidens tegn-baserede samarbejdsaftaler.",
        "checkEmail": "Tjek din e-mail",
        "returnToSignIn": "Tilbage til login",
        "loadingSignIn": "Logger ind...",
        "loadingSignUp": "Opretter konto..."
    },
    "nav": {
        "dashboard": "Kontrolpanel",
        "templates": "Skabeloner",
        "settings": "Indstillinger",
        "signOut": "Log ud"
    },
    "footer": {
        "about": "Om os",
        "contact": "Kontakt",
        "privacy": "Privatlivspolitik",
        "terms": "Betingelser"
    },
    "shared": {
        "cookieBanner": {
            "title": "Vi værdsætter dit privatliv",
            "description": "Paktio bruger cookies til at forbedre din oplevelse og sikre dokumentintegritet i henhold til EU-lovgivning. Ved at klikke på \"Accepter alle\" giver du samtykke til vores brug af cookies til analyse og personligt indhold.",
            "privacyPolicy": "Privatlivspolitik",
            "viewDetails": "Se vores {privacyPolicy} for flere detaljer.",
            "necessary": "Kun nødvendige",
            "acceptAll": "Accepter alle"
        },
        "chatSupport": {
            "title": "Paktio Support",
            "status": "Altid online",
            "greeting": "Hvordan kan vi hjælpe i dag?",
            "description": "Vores juridiske ingeniørteam er klar til at hjælpe dig.",
            "startChat": "Start chat"
        }
    },
    "marketing": {
        "hero": {
            "title": "Paktio",
            "subtitle": "Suveræne dokumenter",
            "description": "High-end AI-kontraktudarbejdelse med præcision på tegnniveau og SHA-256 dokumentintegritet til det skandinaviske juridiske landskapet.",
            "ctaStart": "Start gratis",
            "ctaSignIn": "Log ind",
            "registerInterest": "Tilmeld interesse"
        },
        "interestForm": {
            "title": "Tilmeld interesse",
            "description": "Efterlad din e-mail og en besked for at holde dig opdateret om vores lancering.",
            "email": "E-mailadresse",
            "message": "Din besked",
            "placeholder": "Jeg er interesseret i at bruge Paktio til...",
            "send": "Send interesse",
            "success": "Tak for din interesse!"
        },
        "features": {
            "integrity": {
                "label": "Integritet",
                "text": "Kryptografisk bevis for enhver aftale via SHA-256 integritetsudløsere."
            },
            "intelligence": {
                "label": "Intelligens",
                "text": "AI-native udarbejdelse ved hjælp af Gemini 1.5 Pro med kontekstbevidste juridiske skemaer."
            },
            "compliance": {
                "label": "Overholdelse",
                "text": "eIDAS AdES-kompatible signaturer optimeret til EØS og de skandinaviske markeder."
            }
        }
    },
    "dashboard": {
        "workspace": "Workspace",
        "precision": "Præcision på tegnniveau lige ved hånden.",
        "insights": {
            "drafts": "Udkast",
            "awaiting": "Afventer",
            "signed": "Signeret"
        },
        "pipeline": "Styringspipeline",
        "templates": {
            "title": "Systemskabeloner",
            "subtitle": "Standardiserede rammer for hurtig udarbejdelse.",
            "browseAll": "Gennemse alle"
        },
        "security": {
            "title": "Dokumentsikkerhed",
            "description": "Paktio forsegler hvert udkast med en unik **SHA-256-hash**, hvilket sikrer, at den version, der underskrives, er præcis det, du godkendte."
        },
        "links": {
            "title": "Nyttige links",
            "compliance": "Overholdelsesguide",
            "api": "API-dokumentation"
        },
        "noAgreements": "Ingen aftaler i denne kategori.",
        "draftFirst": "Udarbejd din første kontrakt",
        "auditLog": "Revisionslog",
        "useTemplate": "Brug"
    },
    "editor": {
        "status": {
            "drafting": "Udarbejdelse",
            "edit": "Rediger",
            "saving": "Gemmer ændringer før signaturanmodning...",
            "errorGenerating": "Fejl ved generering av kontrakt",
            "savedTemplate": "Gemt som skabelon",
            "savedDraft": "Gemt udkast",
            "failedSave": "Kunne ikke gemme",
            "dispatching": "Sender..."
        },
        "actions": {
            "saveDraft": "Gem udkast",
            "save": "Gem",
            "requestSignature": "Anmod om signatur",
            "send": "Send",
            "sent": "Sendt",
            "preview": "Gennemse dokument"
        },
        "architect": {
            "title": "Juridisk arkitekt",
            "placeholder": "Udkast til en 6-måneders konsulentfold...",
            "generate": "Generer udkast",
            "tools": "Værktøjer"
        },
        "roles": {
            "title": "Dokumentroller",
            "primary": "Primær enhed",
            "counterparty": "Modpart",
            "primaryPlaceholder": "f.eks. Udlejer",
            "counterpartyPlaceholder": "f.eks. Lejer"
        },
        "canvas": {
            "untitled": "Unavngiven kontrakt",
            "emptyTitle": "Lav fra bunden eller brug AI",
            "emptyDescription": "Begynd at skrive nedenfor for at opbygge din kontrakt manuelt, eller brug den juridiske arkitekt som udgangspunkt.",
            "addHeader": "Tilføj overskrift",
            "addClause": "Tilføj klausul",
            "chooseTemplates": "Vælg fra skabeloner",
            "insertSection": "Indsæt sektion",
            "header": "Overskrift",
            "clause": "Klausul",
            "listItem": "Listepunkt",
            "footer": "Sidefod",
            "deleteBlock": "Slet blok",
            "moveUp": "Flyt op",
            "moveDown": "Flyt ned"
        },
        "modal": {
            "requestTitle": "Send anmodning",
            "requestDescription": "Indtast modpartens e-mail. De vil modtage et sikkert link til at underskrive.",
            "previewTitle": "Gennemse dokument",
            "previewSubtitle": "Sådan vil din kontrakt se ud for underskrivere.",
            "signaturePlaceholder": "Signaturpladsholder"
        }
    },
    "history": {
        "title": "Kontrakthistorik",
        "details": "Dokumentdetaljer",
        "subtitle": "Uforanderlig registrering af denne juridiske aftale.",
        "actions": {
            "goToSigning": "Gå til underskrift",
            "sign": "Underskriv"
        },
        "signatures": {
            "title": "Registrerede underskrifter",
            "signedOn": "Underskrevet den",
            "verified": "Verificeret",
            "noSignatures": "Ingen underskrifter registreret endnu."
        },
        "info": {
            "title": "Dokumentinfo",
            "referenceId": "Reference-ID",
            "mathematicalSignature": "Matematisk underskrift",
            "version": "Version",
            "status": "Status",
            "integrityNotice": "Alle underskrifter er kryptografisk bundet til det hash, der vises ovenfor. Ændring af indhold vil annullere denne registrering."
        }
    },
    "templates": {
        "title": "Skabelonbibliotek",
        "subtitle": "Kuraterede rammer for hurtig udarbejdelse af høj kvalitet.",
        "available": "Systemskabeloner tilgængelige",
        "featured": "Udvalgte rammer"
    },
    "upgrade": {
        "title": "Vælg din plan",
        "subtitle": "High-end aftalestyring skræddersyet til skandinavisk præcision.",
        "current": "Nuværende plan",
        "monthly": "/måned",
        "currentLabel": "Din nuværende plan",
        "upgradeTo": "Opgrader til ",
        "tiers": {
            "starter": {
                "name": "Starter",
                "price": "0 kr.",
                "description": "Perfekt til freelancere. 3 kontrakter/måned.",
                "features": [
                    "AI-kontraktudarbejdelse",
                    "SHA-256 integritet",
                    "Offentlige underskriftslinks"
                ]
            },
            "pro": {
                "name": "Pro",
                "price": "290 kr.",
                "description": "Til små teams og juridiske professionelle.",
                "features": [
                    "Ubegrænset antal kontrakter",
                    "To-faktor autentificering",
                    "Brugerdefineret branding",
                    "Prioriteret support"
                ]
            }
        }
    },
    "settings": {
        "title": "Brugerindstillinger",
        "loginRequired": "Venligst log ind",
        "personal": {
            "title": "Personlige oplysninger",
            "fullName": "Fulde navn",
            "phone": "Telefonnummer",
            "email": "E-mail",
            "locale": "Sprog",
            "save": "Gem ændringer"
        },
        "security": {
            "title": "Sikkerhed & MFA",
            "description": "To-faktor autentificering tilføjer et ekstra lag sikkerhed til din konto.",
            "manage": "Administrer MFA",
            "activate": "Aktiver MFA"
        }
    },
    "pages": {
        "contact": {
            "title": "Kontakt os",
            "subtitle": "Vi er her for at hjælpe. Kontakt vores team for support, forespørgsler eller partnerskabsmuligheder.",
            "getInTouch": "Kontakt os",
            "hq": "Hovedkvarter",
            "details": "For generelle forespørgsler or support, send os venligst en e-mail direkte eller brug chat-widgetten, hvis den er tilgængelig."
        },
        "about": {
            "title": "Om Paktio",
            "subtitle": "Defineret af integritet. Drevet af intelligens. Sikret af matematik.",
            "mission": {
                "title": "Vores mission",
                "content": "Vi genopfinder juridiske aftaler til den digitale tidsalder. Vi mener, at en kontrakt bør være mere end blot tekst på en side – den bør være en uforanderlig, verificerbar kilde til sandhed."
            },
            "sovereignty": {
                "title": "Suveræne dokumenter",
                "content": "I en verden af flygtige data står Paktio for varighed. Vi bygger værktøjer, der respekterer aftalens hellighed, og sikrer, at det du underskriver, er præcis det, der forbliver i protokollen, for evigt."
            },
            "roots": {
                "title": "Skandinaviske rødder",
                "content": "Paktio emmer af de skandinaviske principper om gennemsigtighed, tillid og minimalistisk design. Vi fjerner det unødvendige for at fokusere på det, der conte: selve aftalen."
            }
        },
        "privacy": {
            "title": "Privatlivspolitik",
            "subtitle": "Hos Paktio er dokumentintegritet og datasuverænitet kernen i alt, hvad we build. Denne politik beskriver, hvordan vi beskytter dine oplysninger i overensstemmelse med GDPR- og EØS-standarder.",
            "sections": {
                "sovereignty": {
                    "title": "1. Datasuverænitet",
                    "content": "Vi mener, at dine data tilhører dig. Paktio fungerer som vogter af dine juridiske aftaler. Alle data, der indtastes i Paktio, opbevares sikkert i EØS."
                },
                "integrity": {
                    "title": "2. Dokumentintegritet",
                    "content": "Vores \"integritetsregel\" bruger SHA-256-hashing til at sikre, at når et dokument er underskrevet, kan dets tilstand ikke ændres uden at annullere underskrifterne. Dette kryptografiske bevis gemmes sammen med dine dokument metadata."
                },
                "rights": {
                    "title": "3. Dine rettigheder",
                    "content": "I henhold til EU-lovgivningen har du ret til at få adgang til, rette eller slette dine personlige data. Du kan til enhver tid anmode om en fuld eksport af dine kontodata via siden Indstillinger."
                }
            }
        },
        "terms": {
            "title": "Servicevilkår",
            "lastUpdated": "Sidst opdateret: 21. januar 2026",
            "sections": [
                {
                    "title": "1. Accept og aftale om vilkår",
                    "content": "Disse servicevilkår (\"Vilkårene\") regulerer din adgang til og brug af Paktio (\"Platformen\"), en webbaseret tjeneste til oprettelse, underskrift og styring af digitale aftaler. Ved at oprette en konto eller bruge Platformen accepterer du at være bundet af disse Vilkår og vores privatlivspolitik. Hvis du ikke accepterer disse vilkår, skal du øjeblikkeligt ophøre med al brug af Platformen."
                },
                {
                    "title": "2. Definitioner",
                    "content": "\"Platformen\" betyder Paktio-webstedet, applikationen og alle tilknyttede tjenester, herunder \"Legal Architect\"-værktøjer og funktioner til elektronisk underskrift.\n\"Bruger\" (eller \"du\") betyder den person eller enhed, der tilgår Platformen.\n\"AdES\" refererer til avancerede elektroniske underskrifter som defineret i EU eIDAS-forordningen (nr. 910/2014).\n\"Integritetsreglen\" refererer til den kryptografiske verifikationsmetode, som Paktio anvender til at forsegle dokumenttilstande.\n\"Brugerindhold\" refererer til data, tekst eller dokumenter, der uploades eller udarbejdes af Brugeren på Platformen."
                },
                {
                    "title": "3. Beskrivelse af tjenesten",
                    "content": "Paktio leverer avancerede værktøjer til aftalestyring, herunder AI-baseret drafting med præcision på tegnniveau og kryptografisk dokumentintegritet. Platformen er i øjeblikket i en MVP- (Minimum Viable Product) og testfase. Funktioner leveres som de er for at lette moderne juridiske arbejdsgange."
                },
                {
                    "title": "4. Brugerkonti og sikkerhed",
                    "content": "Du er ansvarlig for at opretholde sikkerheden på din konto, herunder brug af stærke adgangskoder og aktivering af multifaktor-autentificering (MFA), hvor det er tilgængeligt. Paktio er ikke ansvarlig for uautoriseret adgang som følge af usikker kontohåndtering. Du accepterer at give nøjagtige oplysninger og straks at underrette os om enhver uautoriseret brug af din konto."
                },
                {
                    "title": "5. Juridisk gyldighed og overholdelse",
                    "content": "Paktio leverer værktøjer til avancerede elektroniske underskrifter (AdES) i overensstemmelse med eIDAS-standarder. Det er dog dit eget ansvar at sikre, at dine specifika aftaler ikke kræver en kvalificeret elektronisk underskrift (QES) eller andre fysiske formaliteter i henhold til lokal lovgivning. Paktio garanterer ikke for retskraften af et specifikt dokument i en specifik jurisdiktion."
                },
                {
                    "title": "6. Integritetsreglen",
                    "content": "Paktio håndhæver en streng politik for dokumentintegritet. Hvert dokument forsegles med en unik SHA-256-hash. Enhver ændring af dokumentindhold, efter at en underskrift er påført, vil medføre øjeblikkelig og uigenkaldelig annullering af alle eksisterende underskrifter for den version. Dette sikrer, at det, du underskriver, er præcis det, der forbliver registreret."
                },
                {
                    "title": "7. Acceptabel brug og forbudt adfærd",
                    "content": "Du accepterer kun at bruge Platformen til lovlige formål. Forbudt adfærd omfatter: forsøg på at forstyrre Platformens kryptografiske sikkerhed eller Integritetsreglen; brug af AI-værktøjer til at generere svigagtige eller ulovlige dokumenter; upload af indhold, der krænker tredjeparts intellektuelle ejendomsrettigheder eller privatliv; og forsøg på at dekompilere eller udtrække kildekoden til Platformen."
                },
                {
                    "title": "8. Intellektuelle ejendomsrettigheder",
                    "content": "Alle rettigheder, titler og interesser i og til Platformen (undtagen Brugerindhold) er og forbliver Paktios eksklusive ejendom. Dette omfatter al software, designelementer, æstetiske tokens og AI-baseret drafting-logik."
                },
                {
                    "title": "9. Brugerindhold og licensbevilling",
                    "content": "Du beholder alle ejendomsrettigheder til dit Brugerindhold. Du giver Paktio en begrænset, ikke-eksklusiv, royaltyfri licens til at hoste, lagre og behandle dit indhold udelukkende med det formål at levere tjenesten. Paktio fungerer som databehandler for dine data i overensstemmelse med GDPR- og EØS-standarder."
                },
                {
                    "title": "10. Databeskyttelse og privatliv (GDPR)",
                    "content": "Dit privatliv og dinumentsuverænitet er centrale for Paktio. Vi håndterer alle personoplysninger i overensstemmelse med vores privatlivspolitik. Ved at bruge Platformen anerkender du, at vi gemmer dokumentmetadata og kryptografiske hashes for at sikre varigheden og integriteten af dine aftaler."
                },
                {
                    "title": "11. Ansvarsfriskrivninger: \"SOM DEN ER\" og nøjagtighed",
                    "content": "Paktio æ r en teknologiudbyder, ikke et advokatfirma. Platformen leveres \"SOM DEN ER\" uden nogen form for garantier. Paktio er et teknisk værktøj designet til at lette oprettelsen af aftaler; det er brugernes eget ansvar at bekræfte den juridiske gyldighed og overholdelse af lovgivning for ethvert indhold i kontrakter eller aftaler. Vi yder ikke juridisk rådgivning. Alle AI-genererede utkast bør gennemgås af en kvalificeret juridisk ekspert før brug."
                },
                {
                    "title": "12. Ansvarsbegrænsning",
                    "content": "I det maksimale omfang tilladt af gældende lovgivning er Paktio eller dets operatører ikke ansvarlige for skader eller tab. I betragtning af dens nuværende test/MVP-status er Paktios samlede ansvar begrænset til nul (0 DKK/NOK) for alle krav."
                },
                {
                    "title": "13. Skadesløsholdelse",
                    "content": "Du accepterer at skadesløsholde Paktio for ethvert krav, ansvar eller udgifter (herunder advokatomkostninger), der opstår som følge af din misbrug af Platformen, din overtrædelse af disse Vilkår or din krænkelse af tredjeparts rettigheder."
                },
                {
                    "title": "14. Opsigelse og suspendering",
                    "content": "Vi forbeholder os retten til at suspendere eller lukke din konto efter eget skøn, uden varsel, for adfærd, som we believe overtræder disse Vilkår or er skadelig for andre brugere or Platformens integritet."
                },
                {
                    "title": "15. Ändring af vilkårene",
                    "content": "Paktio og dets operatører forbeholder sig retten til at opdatere disse Vilkår fra tid til anden. Vi vil underrette dig om væsentlige ændringer ved at opslå de nye Vilkår på webstedet. Fortsat brug af Platformen efter äendringer udgör din accept af de reviderede Vilkår."
                },
                {
                    "title": "16. Lovvalg og värneting",
                    "content": "Disse Vilkår og enhver tvist i forbindelse hermed skal være underlagt lovgivningen i Norge. Enhver retssag skal udelukkende anlægges ved domstolene i Oslo, Norge."
                },
                {
                    "title": "17. Kontaktoplysninger",
                    "content": "For spørgsmål vedrørende disse Vilkår eller for support, kontakt venligst support@paktio.com."
                }
            ]
        }
    },
    "mfa": {
        "verifyTitle": "To-faktor autentificering",
        "verifySubtitle": "Indtast koden fra din autentiseringsapp.",
        "verifyLabel": "Bekræft",
        "setupTitle": "Aktivér to-faktor autentificering",
        "setupSubtitle": "Sikr din Paktio-konto med en autentiseringsapp (f.eks. Google Authenticator, Authy).",
        "step1Description": "Klik nedenfor for at generere din unikke QR-kode",
        "startSetup": "Start opsætning",
        "step2Scan": "Scan denne kode med din autentiseringsapp.",
        "step2Verify": "Indtast den 6-cifrede kode fra din app.",
        "verifyActivate": "Bekræft og aktivér",
        "step3Success": "MFA aktiveret",
        "step3Description": "Din konto er nu mere sikker."
    },
    "pdf": {
        "reference": "Reference",
        "hash": "Hash",
        "version": "Version",
        "name": "Navn",
        "email": "E-mail",
        "phone": "Telefon",
        "address": "Adresse",
        "dob": "Fødselsdato",
        "ssn": "CPR-nummer",
        "noParties": "Ingen parter registreret.",
        "attachments": "Bilag",
        "noAttachments": "Ingen bilag",
        "signatures": "Underskrifter",
        "integrityNotice": "Denne kontrakt er underskrevet elektronisk ved hjælp af PAKTIOs e-underskriftstjeneste. Underskrifterne med detaljerede oplysninger er vedlagt i et separat underskriftscertifikat i slutningen af denne PDF.",
        "learnMore": "Lær mere om PAKTIOs elektroniske underskrifter på",
        "footerNotice": "Digitalt underskrevet og verificeret",
        "certificateTitle": "Digitalt underskriftscertifikat",
        "certificateSubtitle": "Dette certifikat bekræfter dokumentets integritet.",
        "documentInfo": "Dokumentoplysninger",
        "signingRecords": "Underskriftsprotokoller og håndskrevne underskrifter",
        "signedAt": "Underskrevet",
        "noImage": "Intet billede",
        "capturedSignature": "CAPTURED SIGNATURE"
    }
}